futcli/__init__.py
futcli/evolutions.py
futcli/futcli.py
futcli/sbc.py
futcli/urls.py
futcli-0.1.2.dist-info/LICENSE
futcli-0.1.2.dist-info/METADATA
futcli-0.1.2.dist-info/WHEEL
futcli-0.1.2.dist-info/entry_points.txt
futcli-0.1.2.dist-info/top_level.txt
futcli-0.1.2.dist-info/RECORD
