Metadata-Version: 2.1
Name: futcli
Version: 0.1.2
Summary: A command-line interface tool for fetching FC Ultimate Team data (futgg scraper)
Home-page: https://github.com/ejamilasan/futcli
Author: Edwin Amilasan Jr.
Author-email: ejamilasan@gmail.com
Classifier: Programming Language :: Python :: 3
Classifier: License :: OSI Approved :: GNU General Public License v3 (GPLv3)
Classifier: Operating System :: OS Independent
License-File: LICENSE
Requires-Dist: requests
Requires-Dist: beautifulsoup4
Requires-Dist: tabulate
